hotc/__init__.py
hotc/data/hotc_counters.csv
hotc/main.py
hotc-2.0.0.dist-info/LICENSE
hotc-2.0.0.dist-info/WHEEL
hotc-2.0.0.dist-info/METADATA
hotc-2.0.0.dist-info/RECORD
